[
  {
    "duration": "00:00:00.0100005",
    "Failed": false,
    "finish": "2016-08-05T14:31:30.8771427+09:00",
    "name": "TestReadRawRecord",
    "start": "2016-08-05T14:31:30.8671422+09:00",
    "output": "0\r\n1#0\u001f1#0\u001f0#44\u001f692#^B2008/2009^CO^X!NOZO^D42^E3^Z14.\r\n2#0\u001f2#0\u001f0#31\u001f692#^B2007/2008^CO^AФКТИ^D30^E4^F7.50\r\n3#0\u001f3#0\u001f0#31\u001f225#^AТруды^VВып.664^FМосковский энер"
  },
  {
    "duration": "00:00:00.0060004",
    "Failed": false,
    "finish": "2016-08-05T14:31:31.3831717+09:00",
    "name": "TestVersion",
    "start": "2016-08-05T14:31:31.3771713+09:00",
    "output": "Version: 64.2014, MaxClients: 100000, ConnectedClients: 1, Organization: Иркутский государственный технический университет"
  }
]