[
  {
    "duration": "00:00:00.0100000",
    "Failed": false,
    "finish": "2016-08-01T10:52:00.9601636+09:00",
    "name": "TestConnectionFailure",
    "start": "2016-08-01T10:52:00.9501636+09:00",
    "output": "bad"
  },
  {
    "duration": "00:00:00.0050000",
    "Failed": false,
    "finish": "2016-08-01T10:52:01.4661647+09:00",
    "name": "TestFormatVerbatim",
    "start": "2016-08-01T10:52:01.4611647+09:00",
    "output": "Привет, мир!"
  },
  {
    "duration": "00:00:00.0050000",
    "Failed": false,
    "finish": "2016-08-01T10:52:01.9741678+09:00",
    "name": "TestFormatOneRecord",
    "start": "2016-08-01T10:52:01.9691678+09:00",
    "output": ""
  },
  {
    "duration": "00:00:00.0100000",
    "Failed": false,
    "finish": "2016-08-01T10:52:02.4841685+09:00",
    "name": "TestFormatVirtualRecord",
    "start": "2016-08-01T10:52:02.4741685+09:00",
    "output": ""
  },
  {
    "duration": "00:00:00.0050000",
    "Failed": false,
    "finish": "2016-08-01T10:52:02.9951698+09:00",
    "name": "TestFormatThreeRecords",
    "start": "2016-08-01T10:52:02.9901698+09:00",
    "output": ""
  },
  {
    "duration": "00:00:00.0050000",
    "Failed": false,
    "finish": "2016-08-01T10:52:03.5011706+09:00",
    "name": "TestVersion",
    "start": "2016-08-01T10:52:03.4961706+09:00",
    "output": "Version: 0, MaxClients: 0, ConnectedClients: 0, Organization: "
  }
]